semantic_link_functions_geopandas-0.12.2.dist-info/licenses/LICENSE.txt
sempy_functions_geopandas/__init__.py
sempy_functions_geopandas/_geopandas.py
semantic_link_functions_geopandas-0.12.2.dist-info/METADATA
semantic_link_functions_geopandas-0.12.2.dist-info/WHEEL
semantic_link_functions_geopandas-0.12.2.dist-info/top_level.txt
semantic_link_functions_geopandas-0.12.2.dist-info/RECORD
